{"cameraMode":{"drawMode":0,"name":"Shaded","section":"Shading Mode"},"sceneLighting":true,"audioPlay":false,"sceneViewState":{"m_AlwaysRefresh":false,"showFog":true,"showSkybox":true,"showFlares":true,"showImageEffects":true,"showParticleSystems":true,"showVisualEffectGraphs":true,"m_FxEnabled":true},"in2DMode":false,"pivot":{"x":-4.77560567855835,"y":8.696211814880371,"z":-10.358445167541504},"rotation":{"x":0.016166318207979204,"y":-0.05337107554078102,"z":-0.000865166774019599,"w":-0.9984453320503235},"size":9.166329383850098,"orthographic":false}